hashtray/__about__.py
hashtray/__init__.py
hashtray/cli.py
hashtray/enumerator.py
hashtray/get_elements.py
hashtray/get_gravatar.py
hashtray/permutator.py
hashtray/data/__init__.py
hashtray/data/email_services.json
hashtray/data/email_services_full.json
hashtray/data/email_services_long.json
hashtray-0.1.1.dist-info/METADATA
hashtray-0.1.1.dist-info/WHEEL
hashtray-0.1.1.dist-info/entry_points.txt
hashtray-0.1.1.dist-info/licenses/LICENSE
hashtray-0.1.1.dist-info/RECORD
