Metadata-Version: 2.4
Name: hashtray
Version: 0.1.1
Summary: hashtray is an OSINT tool for Gravatar. Find Gravatar account from an email and find an email from a Gravatar account.
Project-URL: Homepage, https://github.com/balestek/hashtray
Project-URL: Bug Tracker, https://github.com/balestek/hashtray/issues
Author: balestek
License:                     GNU GENERAL PUBLIC LICENSE
License-File: LICENSE
Keywords: email,gravatar,hash,information-gathering,investigation,md5,md5-hash,open-source-intelligence,osint,osint-gravatar,osint-python,osint-tool,osint-tools,pipenv,pipx,pypi,python
Classifier: Development Status :: 4 - Beta
Classifier: Environment :: Console
Classifier: License :: OSI Approved :: GNU General Public License v3 (GPLv3)
Classifier: Natural Language :: English
Classifier: Operating System :: OS Independent
Classifier: Programming Language :: Python :: 3
Classifier: Programming Language :: Python :: 3.10
Classifier: Programming Language :: Python :: 3.11
Classifier: Programming Language :: Python :: 3.12
Classifier: Programming Language :: Python :: 3.13
Classifier: Programming Language :: Python :: 3.14
Requires-Python: >=3.10
Requires-Dist: httpx
Requires-Dist: rich
Requires-Dist: scrapling[fetchers]
Requires-Dist: tldextract
Requires-Dist: tqdm
Requires-Dist: unidecode
